sandbox/__init__.py
sandbox/sandbox.py
basic_poetry-2.dist-info/METADATA
basic_poetry-2.dist-info/WHEEL
basic_poetry-2.dist-info/RECORD
