Metadata-Version: 2.1
Name: basic-poetry
Version: 2
Summary: basic dependencies for poetry
Author: BloodSpy
Author-email: hahaclassik@gmail.com
Requires-Python: >=3.11,<4.0
Classifier: Programming Language :: Python :: 3
Classifier: Programming Language :: Python :: 3.11
Requires-Dist: flake8 (>=6.0.0,<7.0.0)
Requires-Dist: flake8-alfred (>=1.1.1,<2.0.0)
Requires-Dist: flake8-bugbear (>=23.3.23,<24.0.0)
Requires-Dist: flake8-builtins (>=2.1.0,<3.0.0)
Requires-Dist: flake8-commas (>=2.1.0,<3.0.0)
Requires-Dist: flake8-comprehensions (>=3.12.0,<4.0.0)
Requires-Dist: flake8-docstrings (>=1.7.0,<2.0.0)
Requires-Dist: flake8-import-order (>=0.18.2,<0.19.0)
Requires-Dist: flake8-quotes (>=3.3.2,<4.0.0)
Requires-Dist: flake8-variables-names (>=0.0.5,<0.0.6)
Requires-Dist: mypy (>=1.2.0,<2.0.0)
Requires-Dist: pep8-naming (>=0.13.3,<0.14.0)
